tree-sitter-jinja2/language_dsoinfo.py
tree-sitter-jinja2/liblanguage.dylib
tree_sitter_jinja2/__init__.py
tree_sitter_jinja2-0.1.0a1.dist-info/METADATA
tree_sitter_jinja2-0.1.0a1.dist-info/WHEEL
tree_sitter_jinja2-0.1.0a1.dist-info/top_level.txt
tree_sitter_jinja2-0.1.0a1.dist-info/RECORD
