Metadata-Version: 2.1
Name: tree-sitter-jinja2
Version: 0.1.0a1
Summary: A Jinja2 grammar for tree-sitter
Home-page: https://github.com/fishtown-analytics/tree-sitter-jinja2
Author: Fishtown Analytics
Author-email: info@fishtownanalytics.com
License: UNKNOWN
Platform: UNKNOWN
Classifier: Programming Language :: Python :: 3
Classifier: Programming Language :: Python :: 3 :: Only
Classifier: Programming Language :: Python :: 3.6
Classifier: Programming Language :: Python :: 3.7
Classifier: Programming Language :: Python :: 3.8
Classifier: Programming Language :: Python :: 3.9
Requires-Python: >=3.6.1
Requires-Dist: tree-sitter (==0.19.0)
Requires-Dist: setuptools-dso (==2.0a1)
